odoo/addons/ssi_lead_operating_unit/README.rst
odoo/addons/ssi_lead_operating_unit/__init__.py
odoo/addons/ssi_lead_operating_unit/__manifest__.py
odoo/addons/ssi_lead_operating_unit/i18n/ssi_lead_operating_unit.pot
odoo/addons/ssi_lead_operating_unit/models/__init__.py
odoo/addons/ssi_lead_operating_unit/models/crm_lead.py
odoo/addons/ssi_lead_operating_unit/security/ir_rule/crm_lead.xml
odoo/addons/ssi_lead_operating_unit/security/res_groups/crm_lead.xml
odoo/addons/ssi_lead_operating_unit/static/description/icon.png
odoo/addons/ssi_lead_operating_unit/views/crm_lead.xml
odoo14_addon_ssi_lead_operating_unit-14.0.1.0.1.dev1.dist-info/METADATA
odoo14_addon_ssi_lead_operating_unit-14.0.1.0.1.dev1.dist-info/WHEEL
odoo14_addon_ssi_lead_operating_unit-14.0.1.0.1.dev1.dist-info/top_level.txt
odoo14_addon_ssi_lead_operating_unit-14.0.1.0.1.dev1.dist-info/RECORD
